quart_jwt_extended/__init__.py
quart_jwt_extended/_version.py
quart_jwt_extended/config.py
quart_jwt_extended/default_callbacks.py
quart_jwt_extended/exceptions.py
quart_jwt_extended/jwt_manager.py
quart_jwt_extended/tokens.py
quart_jwt_extended/utils.py
quart_jwt_extended/view_decorators.py
Quart_JWT_Extended-0.0.6.dist-info/LICENSE
Quart_JWT_Extended-0.0.6.dist-info/METADATA
Quart_JWT_Extended-0.0.6.dist-info/WHEEL
Quart_JWT_Extended-0.0.6.dist-info/top_level.txt
Quart_JWT_Extended-0.0.6.dist-info/RECORD
