Metadata-Version: 2.1
Name: Quart-JWT-Extended
Version: 0.0.6
Summary: Extended JWT integration with Quart
Home-page: https://github.com/greenape/quart-jwt-extended
Author: Jonathan Gray
Author-email: jono@nanosheep.net
License: MIT
Keywords: quart,jwt,json web token
Platform: any
Classifier: Development Status :: 5 - Production/Stable
Classifier: Environment :: Web Environment
Classifier: Intended Audience :: Developers
Classifier: License :: OSI Approved :: MIT License
Classifier: Operating System :: OS Independent
Classifier: Programming Language :: Python :: 3.7
Classifier: Programming Language :: Python :: 3.8
Classifier: Topic :: Internet :: WWW/HTTP :: Dynamic Content
Classifier: Topic :: Software Development :: Libraries :: Python Modules
Requires-Python: >=3.7
License-File: LICENSE
Requires-Dist: Werkzeug (>=1.0.0)
Requires-Dist: Quart (>=0.11)
Requires-Dist: PyJWT (>2.2.0)
Requires-Dist: six
Provides-Extra: asymmetric_crypto
Requires-Dist: cryptography (>=35.0.0) ; extra == 'asymmetric_crypto'
